{
  "name": "experiment",
  "type": "NominalHyperparameter",
  "categories": [
    {
      "category": "RF",
      "children": [
        {
          "name": "number_of_trees",
          "type": "IntegerHyperparameter",
          "lower": 2,
          "upper": 500,
          "default": 500
        },
        {
          "name": "criterion",
          "type": "NominalHyperparameter",
          "categories": [
            {
              "category": "gain_ratio"
            },
            {
              "category": "accuracy"
            },
            {
              "category": "information_gain"
            }
          ],
          "default": "accuracy"
        },
        {
          "name": "maximal_depth",
          "type": "IntegerHyperparameter",
          "lower": 1,
          "upper": 100,
          "default": 10
        },
        {
          "name": "apply_pruning",
          "type": "NominalHyperparameter",
          "categories": [
            {
              "category": "true",
              "children": [
                {
                  "name": "confidence",
                  "type": "FloatHyperparameter",
                  "lower": 0.0,
                  "upper": 1.0,
                  "default": 0.25
                }
              ]
            },
            {
              "category": "false"
            }
          ],
          "default": "true"
        },
        {
          "name": "apply_prepruning",
          "type": "NominalHyperparameter",
          "categories": [
            {
              "category" : "true",
              "children": [
                {
                  "name": "minimal_gain",
                  "type": "FloatHyperparameter",
                  "lower": 0,
                  "upper": 10,
                  "default": 0.1
                },
                {
                  "name": "minimal_leaf_size",
                  "type": "IntegerHyperparameter",
                  "lower": 1,
                  "upper": 500,
                  "default": 500
                },
                {
                  "name": "minimal_size_for_split",
                  "type": "IntegerHyperparameter",
                  "lower": 1,
                  "upper": 10,
                  "default": 4
                },
                {
                  "name": "number_of_prepruning_alternatives",
                  "type": "IntegerHyperparameter",
                  "lower": 1,
                  "upper": 4,
                  "default": 3
                }
              ]
            },
            {"category" : "false"}
          ],
          "default": "true"
        },
        {
          "name": "random_splits",
          "type": "NominalHyperparameter",
          "categories": [
            {
              "category": "true"
            },
            {
              "category": "false"
            }
          ],
          "default": "false"
        },
        {
          "name": "guess_subset_ratio",
          "type": "NominalHyperparameter",
          "categories": [
            {
              "category": "true",
              "children": [
                {
                  "name": "subset_ratio",
                  "type": "FloatHyperparameter",
                  "lower": 0.0,
                  "upper": 1.0,
                  "default": 0.3
                }
              ]
            },
            {
              "category": "false"
            }
          ],
          "default": "true"
        },
        {
          "name": "voting_strategy",
          "type": "NominalHyperparameter",
          "categories": [
            {
              "category": "confidence_vote"
            },
            {
              "category": "majority_vote"
            }
          ],
          "default": "confidence_vote"
        },
        {
          "name": "use_local_random_seed",
          "type": "NominalHyperparameter",
          "categories": [
            {
              "category": "true",
              "children": [
                {
                  "name": "local_random_seed",
                  "type": "IntegerHyperparameter",
                  "lower": 1992,
                  "upper": 1993,
                  "default": 1992
                }
              ]
            },
            {
              "category": "false"
            }
          ],
          "default": "false"
        },
        {
          "name": "enable_parallel_execution",
          "type": "NominalHyperparameter",
          "categories": [
            {
              "category": "true"
            },
            {
              "category": "false"
            }
          ],
          "default": "true"
        }
      ]
    }
  ]
}